socket_kit/__init__.py
socket_kit/socket_kit.py
socket_kit-0.2.1.dist-info/LICENSE
socket_kit-0.2.1.dist-info/METADATA
socket_kit-0.2.1.dist-info/WHEEL
socket_kit-0.2.1.dist-info/top_level.txt
socket_kit-0.2.1.dist-info/RECORD
