Metadata-Version: 2.1
Name: socket_kit
Version: 0.2.1
Summary: A utility with concise and more fluent code in socket programming
Author: Yiming Liu
Author-email: YimingDesigner@gmail.com
License-File: LICENSE
Requires-Dist: numpy
Requires-Dist: opencv-python
Requires-Dist: mysql-connector-python
